vox_message/__init__.py
vox_message/healthcheck.py
vox_message/jobs.py
vox_message/messages.py
vox_message/models.py
vox_message/serializers.py
vox_message/views.py
vox_messages-0.3.0.dist-info/WHEEL
vox_messages-0.3.0.dist-info/METADATA
vox_messages-0.3.0.dist-info/RECORD
