Metadata-Version: 2.1
Name: vox-messages
Version: 0.3.0
Summary: 
Author: Jhonatan Teixeira
Author-email: jhonatan.teixeira@gmail.com
Requires-Python: >=3.8,<4.0
Classifier: Programming Language :: Python :: 3
Classifier: Programming Language :: Python :: 3.10
Classifier: Programming Language :: Python :: 3.8
Classifier: Programming Language :: Python :: 3.9
Requires-Dist: vox-django
Requires-Dist: vox-kafka
